hemlock/__init__.py
hemlock/_admin_routes.py
hemlock/_custom_types.py
hemlock/_data_frame.py
hemlock/_display_navigation.py
hemlock/_navbar.py
hemlock/_page_css.html
hemlock/_page_js.html
hemlock/_user_routes.py
hemlock/admin_route_utils.py
hemlock/app.py
hemlock/data.py
hemlock/page.py
hemlock/timer.py
hemlock/tree.py
hemlock/user.py
hemlock/functional/__init__.py
hemlock/functional/base.py
hemlock/functional/compile.py
hemlock/functional/test_response.py
hemlock/functional/validate.py
hemlock/questions/__init__.py
hemlock/questions/base.py
hemlock/questions/check.py
hemlock/questions/choice_base.py
hemlock/questions/input.py
hemlock/questions/label.py
hemlock/questions/range.py
hemlock/questions/select.py
hemlock/questions/textarea.py
hemlock/templates/hemlock/check.html
hemlock/templates/hemlock/input.html
hemlock/templates/hemlock/label.html
hemlock/templates/hemlock/page.html
hemlock/templates/hemlock/range.html
hemlock/templates/hemlock/range.js
hemlock/templates/hemlock/select.html
hemlock/templates/hemlock/textarea.html
hemlock/templates/hemlock/textarea.js
hemlock/templates/hemlock/statics/auto_advance.html
hemlock/templates/hemlock/statics/figure.html
hemlock/templates/hemlock/statics/recompile_at_interval.js
hemlock/templates/hemlock/utils/card.html
hemlock/templates/hemlock/utils/feedback.html
hemlock/templates/hemlock/utils/form_text.html
hemlock/templates/hemlock/utils/input_group.html
hemlock/templates/hemlock/utils/label.html
hemlock/templates/hemlock/utils/loading_page.html
hemlock/templates/hemlock/utils/navbar.html
hemlock/utils/__init__.py
hemlock/utils/format.py
hemlock/utils/random.py
hemlock/utils/statics.py
hemlock_survey-1.0.1.dist-info/LICENSE
hemlock_survey-1.0.1.dist-info/METADATA
hemlock_survey-1.0.1.dist-info/WHEEL
hemlock_survey-1.0.1.dist-info/top_level.txt
hemlock_survey-1.0.1.dist-info/RECORD
