Metadata-Version: 2.1
Name: hemlock-survey
Version: 1.0.1
Summary: A python framework for creating online surveys and experiments.
Home-page: https://dsbowen.gitlab.io/hemlock
Author: Dillon Bowen
Author-email: dsbowen@wharton.upenn.edu
Classifier: Programming Language :: Python :: 3
Classifier: License :: OSI Approved :: MIT License
Classifier: Operating System :: OS Independent
Requires-Python: >=3.8
License-File: LICENSE
Requires-Dist: IPython
Requires-Dist: flask
Requires-Dist: flask-login
Requires-Dist: flask-socketio
Requires-Dist: flask-sqlalchemy
Requires-Dist: markdown
Requires-Dist: matplotlib
Requires-Dist: networkx
Requires-Dist: pandas
Requires-Dist: simple-websocket
Requires-Dist: sqlalchemy (<=1.4.49)
Requires-Dist: sqlalchemy-mutable (>=1.0.2)
